redis-stubs/METADATA.toml
redis-stubs/__init__.pyi
redis-stubs/backoff.pyi
redis-stubs/client.pyi
redis-stubs/cluster.pyi
redis-stubs/connection.pyi
redis-stubs/crc.pyi
redis-stubs/credentials.pyi
redis-stubs/exceptions.pyi
redis-stubs/lock.pyi
redis-stubs/ocsp.pyi
redis-stubs/py.typed
redis-stubs/retry.pyi
redis-stubs/sentinel.pyi
redis-stubs/typing.pyi
redis-stubs/utils.pyi
redis-stubs/asyncio/__init__.pyi
redis-stubs/asyncio/client.pyi
redis-stubs/asyncio/cluster.pyi
redis-stubs/asyncio/connection.pyi
redis-stubs/asyncio/lock.pyi
redis-stubs/asyncio/parser.pyi
redis-stubs/asyncio/retry.pyi
redis-stubs/asyncio/sentinel.pyi
redis-stubs/asyncio/utils.pyi
redis-stubs/commands/__init__.pyi
redis-stubs/commands/cluster.pyi
redis-stubs/commands/core.pyi
redis-stubs/commands/helpers.pyi
redis-stubs/commands/parser.pyi
redis-stubs/commands/redismodules.pyi
redis-stubs/commands/sentinel.pyi
redis-stubs/commands/bf/__init__.pyi
redis-stubs/commands/bf/commands.pyi
redis-stubs/commands/bf/info.pyi
redis-stubs/commands/graph/__init__.pyi
redis-stubs/commands/graph/commands.pyi
redis-stubs/commands/graph/edge.pyi
redis-stubs/commands/graph/exceptions.pyi
redis-stubs/commands/graph/node.pyi
redis-stubs/commands/graph/path.pyi
redis-stubs/commands/graph/query_result.pyi
redis-stubs/commands/json/__init__.pyi
redis-stubs/commands/json/commands.pyi
redis-stubs/commands/json/decoders.pyi
redis-stubs/commands/json/path.pyi
redis-stubs/commands/search/__init__.pyi
redis-stubs/commands/search/aggregation.pyi
redis-stubs/commands/search/commands.pyi
redis-stubs/commands/search/query.pyi
redis-stubs/commands/search/result.pyi
redis-stubs/commands/timeseries/__init__.pyi
redis-stubs/commands/timeseries/commands.pyi
redis-stubs/commands/timeseries/info.pyi
redis-stubs/commands/timeseries/utils.pyi
types_redis-4.6.0.20240903.dist-info/METADATA
types_redis-4.6.0.20240903.dist-info/WHEEL
types_redis-4.6.0.20240903.dist-info/top_level.txt
types_redis-4.6.0.20240903.dist-info/RECORD
